wedoc/__init__.py
wedoc/api/__init__.py
wedoc/api/base.py
wedoc/api/document.py
wedoc/api/form.py
wedoc/api/spreadsheet.py
wedoc/client.py
wedoc/exception.py
wedoc/utils.py
wedoc-0.1.23.dist-info/METADATA
wedoc-0.1.23.dist-info/WHEEL
wedoc-0.1.23.dist-info/RECORD
